{"last_update":"4:59 PM, 09 Jul 2026","total":5,"locations":[{"lat":30.894,"lon":75.625,"detection_":49.0,"radiative_":8.8,"sat":"mod","state":"PB","district":"LUDHIANA"},{"lat":30.988,"lon":75.516,"detection_":42.0,"radiative_":6.2,"sat":"mod","state":"PB","district":"JALANDHAR"},{"lat":31.009,"lon":75.47,"detection_":60.0,"radiative_":9.2,"sat":"mod","state":"PB","district":"JALANDHAR"},{"lat":30.903,"lon":75.306,"detection_":68.0,"radiative_":10.8,"sat":"mod","state":"PB","district":"MOGA"},{"lat":30.894,"lon":75.308,"detection_":65.0,"radiative_":9.1,"sat":"mod","state":"PB","district":"MOGA"}],"districts":{"AMRITSAR":0,"BARNALA":0,"BATHINDA":0,"FARIDKOT":0,"FATEHGARH SAHIB":0,"FAZILKA":0,"FIROZPUR":0,"GURDASPUR":0,"HOSHIARPUR":0,"JALANDHAR":2,"KAPURTHALA":0,"LUDHIANA":1,"MANSA":0,"MOGA":2,"MUKTSAR":0,"SBS NAGAR":0,"PATHANKOT":0,"PATIALA":0,"RUPNAGAR":0,"SANGRUR":0,"SAS NAGAR (MOHALI)":0,"TARN TARAN":0}}