{"last_update":"6:31 PM, 14 Nov 2023","total":126,"locations":[{"lat":29.904,"lon":76.384,"detection_":59.0,"radiative_":9.7,"sat":"mod","state":"HR","district":"KAITHAL"},{"lat":29.908,"lon":76.379,"detection_":76.0,"radiative_":20.7,"sat":"mod","state":"HR","district":"KAITHAL"},{"lat":29.702,"lon":76.845,"detection_":66.0,"radiative_":27.3,"sat":"mod","state":"HR","district":"KARNAL"},{"lat":30.249,"lon":77.268,"detection_":67.0,"radiative_":13.3,"sat":"mod","state":"HR","district":"YAMUNANAGAR"},{"lat":30.23,"lon":77.134,"detection_":75.0,"radiative_":18.5,"sat":"mod","state":"HR","district":"AMBALA"},{"lat":30.227,"lon":77.127,"detection_":64.0,"radiative_":8.4,"sat":"mod","state":"HR","district":"YAMUNANAGAR"},{"lat":30.225,"lon":77.143,"detection_":67.0,"radiative_":10.9,"sat":"mod","state":"HR","district":"AMBALA"},{"lat":30.233,"lon":76.679,"detection_":48.0,"radiative_":8.0,"sat":"mod","state":"HR","district":"AMBALA"},{"lat":30.225,"lon":76.686,"detection_":49.0,"radiative_":7.8,"sat":"mod","state":"HR","district":"AMBALA"},{"lat":30.11,"lon":76.78,"detection_":70.0,"radiative_":12.1,"sat":"mod","state":"HR","district":"KURUKSHETRA"},{"lat":30.116,"lon":76.775,"detection_":70.0,"radiative_":12.5,"sat":"mod","state":"HR","district":"KURUKSHETRA"},{"lat":30.033,"lon":77.051,"detection_":71.0,"radiative_":15.3,"sat":"mod","state":"HR","district":"KURUKSHETRA"},{"lat":30.03,"lon":77.067,"detection_":63.0,"radiative_":9.3,"sat":"mod","state":"HR","district":"KURUKSHETRA"},{"lat":29.907,"lon":76.37,"detection_":51.0,"radiative_":8.7,"sat":"mod","state":"HR","district":"KAITHAL"},{"lat":29.882,"lon":76.228,"detection_":75.0,"radiative_":18.3,"sat":"mod","state":"HR","district":null},{"lat":29.586,"lon":76.566,"detection_":58.0,"radiative_":9.1,"sat":"mod","state":"HR","district":"KARNAL"},{"lat":29.24877,"lon":76.90014,"detection_":8.0,"radiative_":2.7,"sat":"npp","state":"HR","district":"PANIPAT"},{"lat":29.34105,"lon":76.49734,"detection_":8.0,"radiative_":2.7,"sat":"npp","state":"HR","district":"JIND"},{"lat":29.33925,"lon":76.48273,"detection_":8.0,"radiative_":3.6,"sat":"npp","state":"HR","district":"JIND"},{"lat":29.3214,"lon":76.27924,"detection_":8.0,"radiative_":3.0,"sat":"npp","state":"HR","district":"JIND"},{"lat":29.47627,"lon":77.07666,"detection_":8.0,"radiative_":5.6,"sat":"npp","state":"HR","district":"KARNAL"},{"lat":29.47372,"lon":77.05409,"detection_":8.0,"radiative_":11.8,"sat":"npp","state":"HR","district":"KARNAL"},{"lat":29.39288,"lon":76.28496,"detection_":8.0,"radiative_":2.1,"sat":"npp","state":"HR","district":"JIND"},{"lat":29.43772,"lon":76.52978,"detection_":8.0,"radiative_":2.4,"sat":"npp","state":"HR","district":"JIND"},{"lat":29.50722,"lon":76.91747,"detection_":8.0,"radiative_":2.8,"sat":"npp","state":"HR","district":"KARNAL"},{"lat":29.52578,"lon":77.04079,"detection_":8.0,"radiative_":2.2,"sat":"npp","state":"HR","district":"KARNAL"},{"lat":29.52087,"lon":76.96774,"detection_":8.0,"radiative_":7.3,"sat":"npp","state":"HR","district":"KARNAL"},{"lat":29.55777,"lon":77.0518,"detection_":8.0,"radiative_":4.1,"sat":"npp","state":"HR","district":"KARNAL"},{"lat":29.58041,"lon":77.08023,"detection_":8.0,"radiative_":6.2,"sat":"npp","state":"HR","district":"KARNAL"},{"lat":29.57958,"lon":77.07743,"detection_":8.0,"radiative_":5.7,"sat":"npp","state":"HR","district":"KARNAL"},{"lat":29.60607,"lon":77.04143,"detection_":8.0,"radiative_":7.3,"sat":"npp","state":"HR","district":"KARNAL"},{"lat":29.52576,"lon":76.37325,"detection_":8.0,"radiative_":3.0,"sat":"npp","state":"HR","district":"JIND"},{"lat":29.53006,"lon":76.34789,"detection_":8.0,"radiative_":1.9,"sat":"npp","state":"HR","district":"JIND"},{"lat":29.49511,"lon":76.03801,"detection_":8.0,"radiative_":3.5,"sat":"npp","state":"HR","district":"JIND"},{"lat":29.57228,"lon":76.60093,"detection_":8.0,"radiative_":18.2,"sat":"npp","state":"HR","district":"KARNAL"},{"lat":29.52674,"lon":76.11446,"detection_":8.0,"radiative_":2.6,"sat":"npp","state":"HR","district":"JIND"},{"lat":29.519,"lon":76.05325,"detection_":8.0,"radiative_":4.8,"sat":"npp","state":"HR","district":"JIND"},{"lat":29.57488,"lon":76.46976,"detection_":8.0,"radiative_":3.8,"sat":"npp","state":"HR","district":"KAITHAL"},{"lat":29.5196,"lon":76.02923,"detection_":8.0,"radiative_":3.4,"sat":"npp","state":"HR","district":"JIND"},{"lat":29.63009,"lon":76.76557,"detection_":8.0,"radiative_":2.2,"sat":"npp","state":"HR","district":"KARNAL"},{"lat":29.6091,"lon":76.59512,"detection_":8.0,"radiative_":2.7,"sat":"npp","state":"HR","district":"KARNAL"},{"lat":29.54953,"lon":76.12041,"detection_":8.0,"radiative_":5.0,"sat":"npp","state":"HR","district":"JIND"},{"lat":29.63629,"lon":76.78526,"detection_":8.0,"radiative_":3.4,"sat":"npp","state":"HR","district":"KARNAL"},{"lat":29.56157,"lon":76.18623,"detection_":8.0,"radiative_":2.1,"sat":"npp","state":"HR","district":"JIND"},{"lat":29.61523,"lon":76.58401,"detection_":8.0,"radiative_":3.9,"sat":"npp","state":"HR","district":"KARNAL"},{"lat":29.54152,"lon":75.85953,"detection_":8.0,"radiative_":1.8,"sat":"npp","state":"HR","district":"HISAR"},{"lat":29.54032,"lon":75.85031,"detection_":8.0,"radiative_":5.7,"sat":"npp","state":"HR","district":"FATEHABAD"},{"lat":29.53492,"lon":75.80891,"detection_":8.0,"radiative_":2.1,"sat":"npp","state":"HR","district":"FATEHABAD"},{"lat":29.63839,"lon":76.69473,"detection_":8.0,"radiative_":3.4,"sat":"npp","state":"HR","district":"KARNAL"},{"lat":29.60829,"lon":76.41177,"detection_":8.0,"radiative_":2.7,"sat":"npp","state":"HR","district":"KAITHAL"},{"lat":29.53877,"lon":75.84744,"detection_":8.0,"radiative_":5.1,"sat":"npp","state":"HR","district":"FATEHABAD"},{"lat":29.61489,"lon":76.43563,"detection_":8.0,"radiative_":3.1,"sat":"npp","state":"HR","district":"KAITHAL"},{"lat":29.54407,"lon":75.86069,"detection_":8.0,"radiative_":3.1,"sat":"npp","state":"HR","district":"HISAR"},{"lat":29.58212,"lon":76.10728,"detection_":8.0,"radiative_":5.3,"sat":"npp","state":"HR","district":"JIND"},{"lat":29.52625,"lon":75.6627,"detection_":8.0,"radiative_":2.3,"sat":"npp","state":"HR","district":"FATEHABAD"},{"lat":29.52978,"lon":75.66211,"detection_":8.0,"radiative_":2.3,"sat":"npp","state":"HR","district":"FATEHABAD"},{"lat":29.67517,"lon":76.7817,"detection_":8.0,"radiative_":5.4,"sat":"npp","state":"HR","district":"KARNAL"},{"lat":29.60707,"lon":76.21974,"detection_":8.0,"radiative_":4.8,"sat":"npp","state":"HR","district":"JIND"},{"lat":29.6845,"lon":76.76472,"detection_":8.0,"radiative_":2.9,"sat":"npp","state":"HR","district":"KARNAL"},{"lat":29.65019,"lon":76.44995,"detection_":8.0,"radiative_":9.4,"sat":"npp","state":"HR","district":"KAITHAL"},{"lat":29.58674,"lon":75.88197,"detection_":8.0,"radiative_":10.0,"sat":"npp","state":"HR","district":"FATEHABAD"},{"lat":29.69388,"lon":76.71683,"detection_":8.0,"radiative_":2.1,"sat":"npp","state":"HR","district":"KARNAL"},{"lat":29.75147,"lon":77.00593,"detection_":8.0,"radiative_":5.6,"sat":"npp","state":"HR","district":"KARNAL"},{"lat":29.71982,"lon":76.74371,"detection_":8.0,"radiative_":6.5,"sat":"npp","state":"HR","district":"KARNAL"},{"lat":29.72354,"lon":76.74313,"detection_":8.0,"radiative_":6.5,"sat":"npp","state":"HR","district":"KARNAL"},{"lat":29.56794,"lon":75.43072,"detection_":8.0,"radiative_":4.4,"sat":"npp","state":"HR","district":"FATEHABAD"},{"lat":29.79288,"lon":76.99956,"detection_":8.0,"radiative_":4.1,"sat":"npp","state":"HR","district":"KARNAL"},{"lat":29.64662,"lon":75.7932,"detection_":8.0,"radiative_":4.0,"sat":"npp","state":"HR","district":"FATEHABAD"},{"lat":29.79611,"lon":76.99617,"detection_":8.0,"radiative_":23.7,"sat":"npp","state":"HR","district":"KARNAL"},{"lat":29.79367,"lon":76.97529,"detection_":8.0,"radiative_":18.0,"sat":"npp","state":"HR","district":"KARNAL"},{"lat":29.79307,"lon":76.97008,"detection_":8.0,"radiative_":12.0,"sat":"npp","state":"HR","district":"KARNAL"},{"lat":29.6835,"lon":76.02959,"detection_":8.0,"radiative_":4.0,"sat":"npp","state":"HR","district":"JIND"},{"lat":29.80889,"lon":76.90947,"detection_":8.0,"radiative_":5.7,"sat":"npp","state":"HR","district":"KARNAL"},{"lat":29.68144,"lon":75.86766,"detection_":8.0,"radiative_":4.7,"sat":"npp","state":"HR","district":"FATEHABAD"},{"lat":29.81264,"lon":76.90889,"detection_":8.0,"radiative_":5.7,"sat":"npp","state":"HR","district":"KARNAL"},{"lat":29.69796,"lon":75.96967,"detection_":8.0,"radiative_":3.8,"sat":"npp","state":"HR","district":"JIND"},{"lat":29.59885,"lon":75.06702,"detection_":8.0,"radiative_":4.7,"sat":"npp","state":"HR","district":"SIRSA"},{"lat":29.86074,"lon":77.02356,"detection_":8.0,"radiative_":2.2,"sat":"npp","state":"HR","district":"KARNAL"},{"lat":29.78433,"lon":76.36543,"detection_":8.0,"radiative_":3.2,"sat":"npp","state":"HR","district":"KAITHAL"},{"lat":29.78251,"lon":76.29132,"detection_":8.0,"radiative_":4.3,"sat":"npp","state":"HR","district":"KAITHAL"},{"lat":29.84678,"lon":76.64089,"detection_":8.0,"radiative_":2.5,"sat":"npp","state":"HR","district":"KAITHAL"},{"lat":29.87009,"lon":76.67837,"detection_":8.0,"radiative_":5.8,"sat":"npp","state":"HR","district":"KAITHAL"},{"lat":29.8451,"lon":76.40787,"detection_":8.0,"radiative_":3.8,"sat":"npp","state":"HR","district":"KAITHAL"},{"lat":29.86134,"lon":76.51109,"detection_":8.0,"radiative_":6.7,"sat":"npp","state":"HR","district":"KAITHAL"},{"lat":29.83207,"lon":76.27061,"detection_":8.0,"radiative_":2.2,"sat":"npp","state":"HR","district":"KAITHAL"},{"lat":29.9289,"lon":77.04816,"detection_":8.0,"radiative_":3.8,"sat":"npp","state":"HR","district":"KARNAL"},{"lat":29.8922,"lon":76.73699,"detection_":8.0,"radiative_":3.6,"sat":"npp","state":"HR","district":"KURUKSHETRA"},{"lat":29.94284,"lon":77.00314,"detection_":8.0,"radiative_":2.9,"sat":"npp","state":"HR","district":"KARNAL"},{"lat":29.85508,"lon":76.2768,"detection_":8.0,"radiative_":3.6,"sat":"npp","state":"HR","district":"KAITHAL"},{"lat":29.91894,"lon":76.64494,"detection_":8.0,"radiative_":4.7,"sat":"npp","state":"HR","district":"KURUKSHETRA"},{"lat":29.91154,"lon":76.34225,"detection_":8.0,"radiative_":30.3,"sat":"npp","state":"HR","district":"KAITHAL"},{"lat":29.98269,"lon":76.78866,"detection_":8.0,"radiative_":1.7,"sat":"npp","state":"HR","district":"KURUKSHETRA"},{"lat":30.05925,"lon":76.82399,"detection_":8.0,"radiative_":2.2,"sat":"npp","state":"HR","district":"KURUKSHETRA"},{"lat":30.01716,"lon":76.38819,"detection_":8.0,"radiative_":3.4,"sat":"npp","state":"HR","district":"KAITHAL"},{"lat":30.08114,"lon":76.8787,"detection_":8.0,"radiative_":3.4,"sat":"npp","state":"HR","district":"KURUKSHETRA"},{"lat":30.01039,"lon":76.30415,"detection_":8.0,"radiative_":4.0,"sat":"npp","state":"HR","district":"KAITHAL"},{"lat":30.10896,"lon":77.04568,"detection_":8.0,"radiative_":1.7,"sat":"npp","state":"HR","district":"KURUKSHETRA"},{"lat":30.08036,"lon":76.74723,"detection_":8.0,"radiative_":3.3,"sat":"npp","state":"HR","district":"KURUKSHETRA"},{"lat":30.02437,"lon":76.29692,"detection_":8.0,"radiative_":5.6,"sat":"npp","state":"HR","district":"KAITHAL"},{"lat":30.10879,"lon":76.62582,"detection_":8.0,"radiative_":6.3,"sat":"npp","state":"HR","district":"AMBALA"},{"lat":30.18017,"lon":77.03236,"detection_":8.0,"radiative_":6.5,"sat":"npp","state":"HR","district":"AMBALA"},{"lat":30.17954,"lon":77.02705,"detection_":8.0,"radiative_":3.8,"sat":"npp","state":"HR","district":"AMBALA"},{"lat":30.17078,"lon":76.92092,"detection_":8.0,"radiative_":2.7,"sat":"npp","state":"HR","district":"KURUKSHETRA"},{"lat":30.15022,"lon":76.74945,"detection_":8.0,"radiative_":4.4,"sat":"npp","state":"HR","district":"KURUKSHETRA"},{"lat":30.09134,"lon":76.26837,"detection_":8.0,"radiative_":4.3,"sat":"npp","state":"HR","district":"KAITHAL"},{"lat":30.19591,"lon":76.93842,"detection_":8.0,"radiative_":2.9,"sat":"npp","state":"HR","district":"KURUKSHETRA"},{"lat":30.20286,"lon":76.96418,"detection_":8.0,"radiative_":2.8,"sat":"npp","state":"HR","district":"AMBALA"},{"lat":30.20663,"lon":76.96359,"detection_":8.0,"radiative_":6.0,"sat":"npp","state":"HR","district":"AMBALA"},{"lat":30.20978,"lon":76.95773,"detection_":8.0,"radiative_":1.8,"sat":"npp","state":"HR","district":"AMBALA"},{"lat":30.24249,"lon":77.04705,"detection_":8.0,"radiative_":3.8,"sat":"npp","state":"HR","district":"AMBALA"},{"lat":30.29577,"lon":77.41086,"detection_":8.0,"radiative_":26.4,"sat":"npp","state":"HR","district":"YAMUNANAGAR"},{"lat":30.25414,"lon":76.91578,"detection_":8.0,"radiative_":8.1,"sat":"npp","state":"HR","district":"AMBALA"},{"lat":30.25352,"lon":76.91052,"detection_":8.0,"radiative_":6.8,"sat":"npp","state":"HR","district":"AMBALA"},{"lat":30.28854,"lon":77.17692,"detection_":8.0,"radiative_":3.6,"sat":"npp","state":"HR","district":"YAMUNANAGAR"},{"lat":30.27422,"lon":76.95563,"detection_":8.0,"radiative_":3.6,"sat":"npp","state":"HR","district":"AMBALA"},{"lat":30.25677,"lon":76.80886,"detection_":8.0,"radiative_":21.3,"sat":"npp","state":"HR","district":"AMBALA"},{"lat":29.00283,"lon":76.22408,"detection_":8.0,"radiative_":0.5,"sat":"npp","state":"HR","district":"HISAR"},{"lat":30.07748,"lon":76.7451,"detection_":8.0,"radiative_":3.0,"sat":"npp","state":"HR","district":"KURUKSHETRA"},{"lat":30.02386,"lon":76.2942,"detection_":8.0,"radiative_":5.4,"sat":"npp","state":"HR","district":"KAITHAL"},{"lat":30.03531,"lon":76.32732,"detection_":8.0,"radiative_":2.6,"sat":"npp","state":"HR","district":"KAITHAL"},{"lat":30.08344,"lon":76.63499,"detection_":8.0,"radiative_":2.6,"sat":"npp","state":"HR","district":"KURUKSHETRA"},{"lat":30.07355,"lon":76.39655,"detection_":8.0,"radiative_":3.5,"sat":"npp","state":"HR","district":"KAITHAL"},{"lat":30.12157,"lon":76.7644,"detection_":8.0,"radiative_":7.8,"sat":"npp","state":"HR","district":"KURUKSHETRA"},{"lat":30.34191,"lon":76.78239,"detection_":8.0,"radiative_":5.5,"sat":"npp","state":"HR","district":"AMBALA"},{"lat":30.3413,"lon":76.77719,"detection_":8.0,"radiative_":5.5,"sat":"npp","state":"HR","district":"AMBALA"},{"lat":30.34068,"lon":76.772,"detection_":8.0,"radiative_":2.4,"sat":"npp","state":"HR","district":"AMBALA"}],"districts":{"AMBALA":18,"BHIWANI":0,"FARIDABAD":0,"FATEHABAD":9,"GURUGRAM":0,"HISAR":3,"JHAJJAR":0,"JIND":17,"KAITHAL":23,"KARNAL":32,"KURUKSHETRA":17,"MAHENDRAGARH":0,"MEWAT":0,"PALWAL":0,"PANCHKULA":0,"PANIPAT":1,"REWARI":0,"ROHTAK":0,"SIRSA":1,"SONIPAT":0,"YAMUNANAGAR":4,"CHARKHI DADRI":0}}