{"last_update":"7:11 PM, 12 Oct 2024","total":97,"locations":[{"lat":30.087,"lon":76.809,"detection_":68.0,"radiative_":10.5,"sat":"mod","state":"HR","district":"KURUKSHETRA"},{"lat":30.038,"lon":76.4,"detection_":66.0,"radiative_":9.0,"sat":"mod","state":"HR","district":"KAITHAL"},{"lat":29.629,"lon":76.994,"detection_":66.0,"radiative_":10.2,"sat":"mod","state":"HR","district":"KARNAL"},{"lat":29.999,"lon":76.844,"detection_":76.0,"radiative_":17.7,"sat":"mod","state":"HR","district":"KURUKSHETRA"},{"lat":29.954,"lon":76.727,"detection_":78.0,"radiative_":21.5,"sat":"mod","state":"HR","district":"KURUKSHETRA"},{"lat":29.412,"lon":76.031,"detection_":45.0,"radiative_":8.1,"sat":"mod","state":"HR","district":"HISAR"},{"lat":30.059,"lon":76.404,"detection_":68.0,"radiative_":9.6,"sat":"mod","state":"HR","district":"KAITHAL"},{"lat":30.077,"lon":76.388,"detection_":61.0,"radiative_":7.9,"sat":"mod","state":"HR","district":"KAITHAL"},{"lat":27.97372,"lon":77.4475,"detection_":8.0,"radiative_":2.6,"sat":"npp","state":"HR","district":"PALWAL"},{"lat":29.54449,"lon":75.39951,"detection_":8.0,"radiative_":5.3,"sat":"npp","state":"HR","district":"FATEHABAD"},{"lat":29.52941,"lon":75.56572,"detection_":8.0,"radiative_":2.1,"sat":"npp","state":"HR","district":"FATEHABAD"},{"lat":29.90979,"lon":76.33125,"detection_":8.0,"radiative_":6.6,"sat":"npp","state":"HR","district":"KAITHAL"},{"lat":30.03153,"lon":76.3981,"detection_":8.0,"radiative_":2.0,"sat":"npp","state":"HR","district":"KAITHAL"},{"lat":30.36753,"lon":77.01102,"detection_":8.0,"radiative_":4.6,"sat":"npp","state":"HR","district":"AMBALA"},{"lat":29.4552,"lon":77.08586,"detection_":8.0,"radiative_":2.0,"sat":"npp","state":"HR","district":"PANIPAT"},{"lat":29.25919,"lon":77.03507,"detection_":8.0,"radiative_":5.8,"sat":"npp","state":"HR","district":"PANIPAT"},{"lat":30.45833,"lon":77.13358,"detection_":8.0,"radiative_":1.4,"sat":"npp","state":"HR","district":"AMBALA"},{"lat":30.45892,"lon":77.13769,"detection_":8.0,"radiative_":4.1,"sat":"npp","state":"HR","district":"AMBALA"},{"lat":30.48172,"lon":77.10378,"detection_":8.0,"radiative_":3.6,"sat":"npp","state":"HR","district":"AMBALA"},{"lat":30.28464,"lon":77.16499,"detection_":8.0,"radiative_":7.8,"sat":"npp","state":"HR","district":"YAMUNANAGAR"},{"lat":30.0626,"lon":76.84637,"detection_":8.0,"radiative_":4.3,"sat":"npp","state":"HR","district":"KURUKSHETRA"},{"lat":30.19631,"lon":76.78791,"detection_":8.0,"radiative_":9.7,"sat":"npp","state":"HR","district":"KURUKSHETRA"},{"lat":29.63789,"lon":76.73506,"detection_":8.0,"radiative_":2.2,"sat":"npp","state":"HR","district":"KARNAL"},{"lat":29.85747,"lon":76.57023,"detection_":8.0,"radiative_":3.5,"sat":"npp","state":"HR","district":"KAITHAL"},{"lat":29.64848,"lon":76.52792,"detection_":8.0,"radiative_":1.8,"sat":"npp","state":"HR","district":"KAITHAL"},{"lat":30.48113,"lon":77.09966,"detection_":8.0,"radiative_":3.6,"sat":"npp","state":"HR","district":"AMBALA"},{"lat":29.13792,"lon":76.92188,"detection_":8.0,"radiative_":1.9,"sat":"npp","state":"HR","district":"SONIPAT"},{"lat":29.15387,"lon":76.98449,"detection_":8.0,"radiative_":2.4,"sat":"npp","state":"HR","district":"SONIPAT"},{"lat":30.00108,"lon":77.17493,"detection_":8.0,"radiative_":6.9,"sat":"npp","state":"HR","district":"YAMUNANAGAR"},{"lat":29.54133,"lon":76.35674,"detection_":8.0,"radiative_":11.0,"sat":"npp","state":"HR","district":"JIND"},{"lat":29.63993,"lon":76.13392,"detection_":8.0,"radiative_":13.0,"sat":"npp","state":"HR","district":"JIND"},{"lat":30.33385,"lon":77.2115,"detection_":8.0,"radiative_":2.1,"sat":"npp","state":"HR","district":"YAMUNANAGAR"},{"lat":29.40253,"lon":76.91002,"detection_":8.0,"radiative_":2.9,"sat":"npp","state":"HR","district":"PANIPAT"},{"lat":30.08279,"lon":77.26502,"detection_":8.0,"radiative_":1.6,"sat":"npp","state":"HR","district":"YAMUNANAGAR"},{"lat":30.52362,"lon":77.1227,"detection_":8.0,"radiative_":8.1,"sat":"npp","state":"HR","district":"AMBALA"},{"lat":29.50063,"lon":76.65422,"detection_":8.0,"radiative_":2.4,"sat":"npp","state":"HR","district":"KARNAL"},{"lat":30.31778,"lon":77.26965,"detection_":8.0,"radiative_":1.6,"sat":"npp","state":"HR","district":"YAMUNANAGAR"},{"lat":30.05878,"lon":76.35173,"detection_":8.0,"radiative_":2.2,"sat":"npp","state":"HR","district":"KAITHAL"},{"lat":29.72638,"lon":76.14576,"detection_":8.0,"radiative_":1.2,"sat":"npp","state":"HR","district":"JIND"},{"lat":30.28486,"lon":76.91343,"detection_":8.0,"radiative_":3.8,"sat":"npp","state":"HR","district":"AMBALA"},{"lat":29.47797,"lon":76.66265,"detection_":8.0,"radiative_":3.7,"sat":"npp","state":"HR","district":"JIND"},{"lat":29.23068,"lon":77.12289,"detection_":8.0,"radiative_":6.0,"sat":"npp","state":"HR","district":"PANIPAT"},{"lat":29.12692,"lon":76.94033,"detection_":8.0,"radiative_":5.1,"sat":"npp","state":"HR","district":"SONIPAT"},{"lat":30.12848,"lon":77.16432,"detection_":8.0,"radiative_":2.1,"sat":"npp","state":"HR","district":"YAMUNANAGAR"},{"lat":28.84929,"lon":77.16019,"detection_":8.0,"radiative_":1.0,"sat":"npp","state":"HR","district":"SONIPAT"},{"lat":29.69599,"lon":76.9468,"detection_":8.0,"radiative_":8.4,"sat":"npp","state":"HR","district":"KARNAL"},{"lat":30.46156,"lon":77.10757,"detection_":8.0,"radiative_":3.2,"sat":"npp","state":"HR","district":"AMBALA"},{"lat":30.03438,"lon":77.02204,"detection_":8.0,"radiative_":2.7,"sat":"npp","state":"HR","district":"KURUKSHETRA"},{"lat":30.0373,"lon":77.0424,"detection_":8.0,"radiative_":1.4,"sat":"npp","state":"HR","district":"KURUKSHETRA"},{"lat":30.33326,"lon":77.08483,"detection_":8.0,"radiative_":2.7,"sat":"npp","state":"HR","district":"AMBALA"},{"lat":29.56687,"lon":75.13309,"detection_":8.0,"radiative_":3.4,"sat":"npp","state":"HR","district":"SIRSA"},{"lat":29.76918,"lon":76.06799,"detection_":8.0,"radiative_":2.1,"sat":"npp","state":"HR","district":"JIND"},{"lat":29.64324,"lon":76.13327,"detection_":8.0,"radiative_":2.9,"sat":"npp","state":"HR","district":"JIND"},{"lat":29.64368,"lon":76.02323,"detection_":8.0,"radiative_":3.4,"sat":"npp","state":"HR","district":"JIND"},{"lat":29.98592,"lon":76.25117,"detection_":8.0,"radiative_":4.5,"sat":"npp","state":"HR","district":"KAITHAL"},{"lat":29.56973,"lon":76.77641,"detection_":8.0,"radiative_":5.3,"sat":"npp","state":"HR","district":"KARNAL"},{"lat":29.41128,"lon":76.12156,"detection_":8.0,"radiative_":2.2,"sat":"npp","state":"HR","district":"JIND"},{"lat":29.78027,"lon":76.34744,"detection_":8.0,"radiative_":1.8,"sat":"npp","state":"HR","district":"KAITHAL"},{"lat":29.78018,"lon":76.27798,"detection_":8.0,"radiative_":2.7,"sat":"npp","state":"HR","district":"KAITHAL"},{"lat":29.73066,"lon":76.24277,"detection_":8.0,"radiative_":1.4,"sat":"npp","state":"HR","district":"KAITHAL"},{"lat":29.03537,"lon":76.5948,"detection_":8.0,"radiative_":1.6,"sat":"npp","state":"HR","district":"ROHTAK"},{"lat":29.71251,"lon":75.85104,"detection_":8.0,"radiative_":5.9,"sat":"npp","state":"HR","district":"FATEHABAD"},{"lat":29.71641,"lon":75.85432,"detection_":8.0,"radiative_":26.0,"sat":"npp","state":"HR","district":"FATEHABAD"},{"lat":29.58334,"lon":75.82766,"detection_":8.0,"radiative_":5.7,"sat":"npp","state":"HR","district":"FATEHABAD"},{"lat":29.50172,"lon":76.38447,"detection_":8.0,"radiative_":3.9,"sat":"npp","state":"HR","district":"JIND"},{"lat":29.48167,"lon":75.80316,"detection_":8.0,"radiative_":2.0,"sat":"npp","state":"HR","district":"HISAR"},{"lat":29.20127,"lon":76.91856,"detection_":8.0,"radiative_":2.3,"sat":"npp","state":"HR","district":"SONIPAT"},{"lat":30.10586,"lon":76.90891,"detection_":8.0,"radiative_":3.4,"sat":"npp","state":"HR","district":"KURUKSHETRA"},{"lat":29.7443,"lon":76.01584,"detection_":8.0,"radiative_":2.1,"sat":"npp","state":"HR","district":null},{"lat":29.73259,"lon":76.00593,"detection_":8.0,"radiative_":13.7,"sat":"npp","state":"HR","district":"JIND"},{"lat":29.82673,"lon":76.40797,"detection_":8.0,"radiative_":0.5,"sat":"npp","state":"HR","district":"KAITHAL"},{"lat":29.46518,"lon":76.00529,"detection_":8.0,"radiative_":2.1,"sat":"npp","state":"HR","district":"HISAR"},{"lat":29.50893,"lon":75.32503,"detection_":8.0,"radiative_":4.0,"sat":"npp","state":"HR","district":"FATEHABAD"},{"lat":29.51493,"lon":75.31971,"detection_":8.0,"radiative_":8.4,"sat":"npp","state":"HR","district":"FATEHABAD"},{"lat":29.48225,"lon":76.03067,"detection_":8.0,"radiative_":1.9,"sat":"npp","state":"HR","district":"JIND"},{"lat":29.52836,"lon":75.29649,"detection_":8.0,"radiative_":1.5,"sat":"npp","state":"HR","district":"SIRSA"},{"lat":28.82128,"lon":76.85234,"detection_":8.0,"radiative_":1.4,"sat":"npp","state":"HR","district":"ROHTAK"},{"lat":29.54473,"lon":76.03864,"detection_":8.0,"radiative_":1.4,"sat":"npp","state":"HR","district":"JIND"},{"lat":28.86493,"lon":76.53719,"detection_":8.0,"radiative_":2.3,"sat":"npp","state":"HR","district":"ROHTAK"},{"lat":29.58273,"lon":75.82372,"detection_":8.0,"radiative_":4.6,"sat":"npp","state":"HR","district":"FATEHABAD"},{"lat":29.78395,"lon":76.32629,"detection_":8.0,"radiative_":3.8,"sat":"npp","state":"HR","district":"KAITHAL"},{"lat":30.22632,"lon":76.78219,"detection_":8.0,"radiative_":2.5,"sat":"npp","state":"HR","district":"AMBALA"},{"lat":30.03393,"lon":76.48396,"detection_":8.0,"radiative_":2.4,"sat":"npp","state":"HR","district":"KURUKSHETRA"},{"lat":29.02267,"lon":77.10745,"detection_":8.0,"radiative_":1.4,"sat":"npp","state":"HR","district":"SONIPAT"},{"lat":28.85121,"lon":77.16335,"detection_":8.0,"radiative_":0.7,"sat":"npp","state":"HR","district":"SONIPAT"},{"lat":28.87054,"lon":77.17146,"detection_":8.0,"radiative_":1.5,"sat":"npp","state":"HR","district":"SONIPAT"},{"lat":29.78349,"lon":76.27734,"detection_":8.0,"radiative_":2.7,"sat":"npp","state":"HR","district":"KAITHAL"},{"lat":29.33718,"lon":75.79112,"detection_":8.0,"radiative_":2.9,"sat":"npp","state":"HR","district":"HISAR"},{"lat":28.30346,"lon":77.36805,"detection_":8.0,"radiative_":1.6,"sat":"npp","state":"HR","district":"FARIDABAD"},{"lat":28.13861,"lon":77.43863,"detection_":8.0,"radiative_":4.2,"sat":"npp","state":"HR","district":"PALWAL"},{"lat":27.94556,"lon":77.45646,"detection_":8.0,"radiative_":9.0,"sat":"npp","state":"HR","district":"PALWAL"},{"lat":28.24616,"lon":77.36205,"detection_":8.0,"radiative_":3.4,"sat":"npp","state":"HR","district":"FARIDABAD"},{"lat":28.13355,"lon":77.4273,"detection_":8.0,"radiative_":3.2,"sat":"npp","state":"HR","district":"PALWAL"},{"lat":28.28819,"lon":77.47745,"detection_":8.0,"radiative_":2.4,"sat":"npp","state":"HR","district":"FARIDABAD"},{"lat":28.19378,"lon":77.35533,"detection_":8.0,"radiative_":2.1,"sat":"npp","state":"HR","district":"PALWAL"},{"lat":28.34762,"lon":77.23141,"detection_":8.0,"radiative_":1.2,"sat":"npp","state":"HR","district":"FARIDABAD"},{"lat":27.975,"lon":77.50444,"detection_":8.0,"radiative_":4.8,"sat":"npp","state":"HR","district":"PALWAL"}],"districts":{"AMBALA":10,"BHIWANI":0,"FARIDABAD":4,"FATEHABAD":8,"GURUGRAM":0,"HISAR":4,"JHAJJAR":0,"JIND":12,"KAITHAL":15,"KARNAL":5,"KURUKSHETRA":9,"MAHENDRAGARH":0,"MEWAT":0,"PALWAL":6,"PANCHKULA":0,"PANIPAT":4,"REWARI":0,"ROHTAK":3,"SIRSA":2,"SONIPAT":8,"YAMUNANAGAR":6,"CHARKHI DADRI":0}}