{"last_update": "8:06 PM, 07 Nov 2023", "PB": {"total": 108, "locations": [{"lat": 31.626, "lon": 75.293, "detection_": 60.0, "radiative_": 16.8, "sat": "mod", "acqdate": "2023-10-05", "acqtime": "13:M3:07", "sensor": "A", "state": "PB", "district": "AMRITSAR"}, {"lat": 31.57, "lon": 75.097, "detection_": 71.0, "radiative_": 24.4, "sat": "mod", "acqdate": "2023-10-05", "acqtime": "13:M3:07", "sensor": "A", "state": "PB", "district": "AMRITSAR"}, {"lat": 31.562, "lon": 75.107, "detection_": 70.0, "radiative_": 23.7, "sat": "mod", "acqdate": "2023-10-05", "acqtime": "13:M3:07", "sensor": "A", "state": "PB", "district": "AMRITSAR"}, {"lat": 30.544, "lon": 76.761, "detection_": 72.0, "radiative_": 22.8, "sat": "mod", "acqdate": "2023-10-05", "acqtime": "13:M3:07", "sensor": "A", "state": "PB", "district": "SAS NAGAR (MOHALI)"}, {"lat": 30.56811, "lon": 76.76017, "detection_": 8.0, "radiative_": 2.4, "sat": "npp", "acqdate": "2023-10-05", "acqtime": "13:M3:58", "sensor": "VF375", "state": "PB", "district": "PATIALA"}, {"lat": 31.45837, "lon": 75.11041, "detection_": 8.0, "radiative_": 1.8, "sat": "npp", "acqdate": "2023-10-05", "acqtime": "13:M3:58", "sensor": "VF375", "state": "PB", "district": "TARN TARAN"}, {"lat": 31.45965, "lon": 75.09705, "detection_": 8.0, "radiative_": 6.6, "sat": "npp", "acqdate": "2023-10-05", "acqtime": "13:M3:58", "sensor": "VF375", "state": "PB", "district": "TARN TARAN"}, {"lat": 31.45629, "lon": 75.09782, "detection_": 8.0, "radiative_": 4.8, "sat": "npp", "acqdate": "2023-10-05", "acqtime": "13:M3:58", "sensor": "VF375", "state": "PB", "district": "TARN TARAN"}, {"lat": 31.45533, "lon": 75.17635, "detection_": 8.0, "radiative_": 2.7, "sat": "npp", "acqdate": "2023-10-05", "acqtime": "13:M3:58", "sensor": "VF375", "state": "PB", "district": "TARN TARAN"}, {"lat": 31.34675, "lon": 75.23923, "detection_": 8.0, "radiative_": 4.9, "sat": "npp", "acqdate": "2023-10-05", "acqtime": "13:M3:58", "sensor": "VF375", "state": "PB", "district": "KAPURTHALA"}, {"lat": 31.33717, "lon": 75.20236, "detection_": 8.0, "radiative_": 3.8, "sat": "npp", "acqdate": "2023-10-05", "acqtime": "13:M3:58", "sensor": "VF375", "state": "PB", "district": "KAPURTHALA"}, {"lat": 31.24581, "lon": 75.33018, "detection_": 8.0, "radiative_": 6.4, "sat": "npp", "acqdate": "2023-10-05", "acqtime": "13:M3:58", "sensor": "VF375", "state": "PB", "district": "KAPURTHALA"}, {"lat": 31.40426, "lon": 75.30902, "detection_": 8.0, "radiative_": 7.2, "sat": "npp", "acqdate": "2023-10-05", "acqtime": "13:M3:58", "sensor": "VF375", "state": "PB", "district": "KAPURTHALA"}, {"lat": 31.26959, "lon": 75.1524, "detection_": 8.0, "radiative_": 10.5, "sat": "npp", "acqdate": "2023-10-05", "acqtime": "13:M3:58", "sensor": "VF375", "state": "PB", "district": "KAPURTHALA"}, {"lat": 31.26411, "lon": 75.14058, "detection_": 8.0, "radiative_": 4.3, "sat": "npp", "acqdate": "2023-10-05", "acqtime": "13:M3:58", "sensor": "VF375", "state": "PB", "district": "KAPURTHALA"}, {"lat": 31.262, "lon": 75.12798, "detection_": 8.0, "radiative_": 28.4, "sat": "npp", "acqdate": "2023-10-05", "acqtime": "13:M3:58", "sensor": "VF375", "state": "PB", "district": "KAPURTHALA"}, {"lat": 31.05534, "lon": 75.21925, "detection_": 8.0, "radiative_": 5.8, "sat": "npp", "acqdate": "2023-10-05", "acqtime": "13:M3:58", "sensor": "VF375", "state": "PB", "district": "JALANDHAR"}, {"lat": 31.46134, "lon": 75.0189, "detection_": 8.0, "radiative_": 3.1, "sat": "npp", "acqdate": "2023-10-05", "acqtime": "13:M3:58", "sensor": "VF375", "state": "PB", "district": "TARN TARAN"}, {"lat": 31.38199, "lon": 75.07099, "detection_": 8.0, "radiative_": 10.1, "sat": "npp", "acqdate": "2023-10-05", "acqtime": "13:M3:58", "sensor": "VF375", "state": "PB", "district": "TARN TARAN"}, {"lat": 31.39154, "lon": 75.08629, "detection_": 8.0, "radiative_": 8.5, "sat": "npp", "acqdate": "2023-10-05", "acqtime": "13:M3:58", "sensor": "VF375", "state": "PB", "district": "TARN TARAN"}, {"lat": 31.4733, "lon": 75.13752, "detection_": 8.0, "radiative_": 3.9, "sat": "npp", "acqdate": "2023-10-05", "acqtime": "13:M3:58", "sensor": "VF375", "state": "PB", "district": "TARN TARAN"}, {"lat": 31.5762, "lon": 75.07647, "detection_": 8.0, "radiative_": 5.3, "sat": "npp", "acqdate": "2023-10-05", "acqtime": "13:M3:58", "sensor": "VF375", "state": "PB", "district": "AMRITSAR"}, {"lat": 31.57563, "lon": 75.076, "detection_": 8.0, "radiative_": 3.7, "sat": "npp", "acqdate": "2023-10-05", "acqtime": "13:M3:58", "sensor": "VF375", "state": "PB", "district": "AMRITSAR"}, {"lat": 31.56206, "lon": 75.05725, "detection_": 8.0, "radiative_": 4.6, "sat": "npp", "acqdate": "2023-10-05", "acqtime": "13:M3:58", "sensor": "VF375", "state": "PB", "district": "AMRITSAR"}, {"lat": 31.72932, "lon": 75.04765, "detection_": 8.0, "radiative_": 4.0, "sat": "npp", "acqdate": "2023-10-05", "acqtime": "13:M3:58", "sensor": "VF375", "state": "PB", "district": "AMRITSAR"}, {"lat": 31.6018, "lon": 75.23522, "detection_": 8.0, "radiative_": 5.7, "sat": "npp", "acqdate": "2023-10-05", "acqtime": "13:M3:58", "sensor": "VF375", "state": "PB", "district": "AMRITSAR"}, {"lat": 31.56334, "lon": 75.04385, "detection_": 8.0, "radiative_": 3.0, "sat": "npp", "acqdate": "2023-10-05", "acqtime": "13:M3:58", "sensor": "VF375", "state": "PB", "district": "AMRITSAR"}, {"lat": 31.62413, "lon": 75.21778, "detection_": 8.0, "radiative_": 1.6, "sat": "npp", "acqdate": "2023-10-05", "acqtime": "13:M3:58", "sensor": "VF375", "state": "PB", "district": "AMRITSAR"}, {"lat": 31.59707, "lon": 75.07611, "detection_": 8.0, "radiative_": 3.2, "sat": "npp", "acqdate": "2023-10-05", "acqtime": "13:M3:58", "sensor": "VF375", "state": "PB", "district": "AMRITSAR"}, {"lat": 31.59468, "lon": 75.3189, "detection_": 8.0, "radiative_": 2.9, "sat": "npp", "acqdate": "2023-10-05", "acqtime": "13:M3:58", "sensor": "VF375", "state": "PB", "district": "AMRITSAR"}, {"lat": 31.59014, "lon": 75.16414, "detection_": 8.0, "radiative_": 3.5, "sat": "npp", "acqdate": "2023-10-05", "acqtime": "13:M3:58", "sensor": "VF375", "state": "PB", "district": "AMRITSAR"}, {"lat": 29.87249, "lon": 75.90696, "detection_": 8.0, "radiative_": 5.4, "sat": "npp", "acqdate": "2023-10-05", "acqtime": "13:M3:58", "sensor": "VF375", "state": "PB", "district": "SANGRUR"}, {"lat": 29.87182, "lon": 75.90289, "detection_": 8.0, "radiative_": 5.4, "sat": "npp", "acqdate": "2023-10-05", "acqtime": "13:M3:58", "sensor": "VF375", "state": "PB", "district": "SANGRUR"}, {"lat": 29.84853, "lon": 75.40435, "detection_": 8.0, "radiative_": 2.7, "sat": "npp", "acqdate": "2023-10-05", "acqtime": "13:M3:58", "sensor": "VF375", "state": "PB", "district": "MANSA"}, {"lat": 30.11458, "lon": 76.13658, "detection_": 8.0, "radiative_": 3.1, "sat": "npp", "acqdate": "2023-10-05", "acqtime": "13:M3:58", "sensor": "VF375", "state": "PB", "district": "PATIALA"}, {"lat": 30.25323, "lon": 76.49812, "detection_": 8.0, "radiative_": 5.7, "sat": "npp", "acqdate": "2023-10-05", "acqtime": "13:M3:58", "sensor": "VF375", "state": "PB", "district": "PATIALA"}, {"lat": 29.87786, "lon": 75.47562, "detection_": 8.0, "radiative_": 3.2, "sat": "npp", "acqdate": "2023-10-05", "acqtime": "13:M3:58", "sensor": "VF375", "state": "PB", "district": "MANSA"}, {"lat": 30.66035, "lon": 74.68905, "detection_": 8.0, "radiative_": 4.9, "sat": "npp", "acqdate": "2023-10-05", "acqtime": "13:M3:58", "sensor": "VF375", "state": "PB", "district": "FARIDKOT"}, {"lat": 30.55099, "lon": 76.7596, "detection_": 8.0, "radiative_": 5.8, "sat": "npp", "acqdate": "2023-10-05", "acqtime": "13:M3:58", "sensor": "VF375", "state": "PB", "district": "SAS NAGAR (MOHALI)"}, {"lat": 30.54479, "lon": 76.7197, "detection_": 8.0, "radiative_": 3.2, "sat": "npp", "acqdate": "2023-10-05", "acqtime": "13:M3:58", "sensor": "VF375", "state": "PB", "district": "PATIALA"}, {"lat": 31.6332, "lon": 75.29354, "detection_": 8.0, "radiative_": 3.2, "sat": "npp", "acqdate": "2023-10-05", "acqtime": "13:M3:58", "sensor": "VF375", "state": "PB", "district": "AMRITSAR"}, {"lat": 31.55774, "lon": 75.28404, "detection_": 8.0, "radiative_": 6.4, "sat": "npp", "acqdate": "2023-10-05", "acqtime": "13:M3:58", "sensor": "VF375", "state": "PB", "district": "AMRITSAR"}, {"lat": 31.05628, "lon": 75.21983, "detection_": 8.0, "radiative_": 3.1, "sat": "npp", "acqdate": "2023-10-05", "acqtime": "13:M3:58", "sensor": "VF375", "state": "PB", "district": "JALANDHAR"}, {"lat": 31.57603, "lon": 75.16299, "detection_": 8.0, "radiative_": 12.5, "sat": "npp", "acqdate": "2023-10-05", "acqtime": "13:M3:58", "sensor": "VF375", "state": "PB", "district": "AMRITSAR"}, {"lat": 31.57268, "lon": 75.16374, "detection_": 8.0, "radiative_": 12.5, "sat": "npp", "acqdate": "2023-10-05", "acqtime": "13:M3:58", "sensor": "VF375", "state": "PB", "district": "AMRITSAR"}, {"lat": 30.19695, "lon": 75.54088, "detection_": 8.0, "radiative_": 1.7, "sat": "npp", "acqdate": "2023-10-05", "acqtime": "13:M3:58", "sensor": "VF375", "state": "PB", "district": "BARNALA"}, {"lat": 31.73106, "lon": 74.9114, "detection_": 8.0, "radiative_": 3.0, "sat": "npp", "acqdate": "2023-10-05", "acqtime": "13:M3:58", "sensor": "VF375", "state": "PB", "district": "AMRITSAR"}, {"lat": 31.73036, "lon": 74.90716, "detection_": 8.0, "radiative_": 2.5, "sat": "npp", "acqdate": "2023-10-05", "acqtime": "13:M3:58", "sensor": "VF375", "state": "PB", "district": "AMRITSAR"}, {"lat": 31.79255, "lon": 74.96382, "detection_": 8.0, "radiative_": 4.9, "sat": "npp", "acqdate": "2023-10-05", "acqtime": "13:M3:58", "sensor": "VF375", "state": "PB", "district": "AMRITSAR"}, {"lat": 31.80741, "lon": 74.96918, "detection_": 8.0, "radiative_": 4.4, "sat": "npp", "acqdate": "2023-10-05", "acqtime": "13:M3:58", "sensor": "VF375", "state": "PB", "district": "AMRITSAR"}, {"lat": 30.84059, "lon": 76.67943, "detection_": 8.0, "radiative_": 1.5, "sat": "npp", "acqdate": "2023-10-05", "acqtime": "13:M3:58", "sensor": "VF375", "state": "PB", "district": "SAS NAGAR (MOHALI)"}, {"lat": 31.65325, "lon": 75.01527, "detection_": 8.0, "radiative_": 4.6, "sat": "npp", "acqdate": "2023-10-05", "acqtime": "13:M3:58", "sensor": "VF375", "state": "PB", "district": "AMRITSAR"}, {"lat": 31.6603, "lon": 75.20529, "detection_": 8.0, "radiative_": 7.0, "sat": "npp", "acqdate": "2023-10-05", "acqtime": "13:M3:58", "sensor": "VF375", "state": "PB", "district": "AMRITSAR"}, {"lat": 31.46205, "lon": 75.02312, "detection_": 8.0, "radiative_": 3.6, "sat": "npp", "acqdate": "2023-10-05", "acqtime": "13:M3:58", "sensor": "VF375", "state": "PB", "district": "TARN TARAN"}, {"lat": 30.93299, "lon": 74.49835, "detection_": 8.0, "radiative_": 2.6, "sat": "npp", "acqdate": "2023-10-05", "acqtime": "13:M3:58", "sensor": "VF375", "state": "PB", "district": "FIROZPUR"}, {"lat": 29.87293, "lon": 76.04841, "detection_": 8.0, "radiative_": 2.1, "sat": "npp", "acqdate": "2023-10-05", "acqtime": "13:M3:58", "sensor": "VF375", "state": "PB", "district": "PATIALA"}, {"lat": 31.02112, "lon": 75.41265, "detection_": 8.0, "radiative_": 2.9, "sat": "npp", "acqdate": "2023-10-05", "acqtime": "13:M3:58", "sensor": "VF375", "state": "PB", "district": "JALANDHAR"}, {"lat": 30.07902, "lon": 76.215, "detection_": 8.0, "radiative_": 3.9, "sat": "npp", "acqdate": "2023-10-05", "acqtime": "13:M3:58", "sensor": "VF375", "state": "PB", "district": "PATIALA"}, {"lat": 30.20165, "lon": 76.00137, "detection_": 8.0, "radiative_": 2.7, "sat": "npp", "acqdate": "2023-10-05", "acqtime": "13:M3:58", "sensor": "VF375", "state": "PB", "district": "SANGRUR"}, {"lat": 30.78525, "lon": 74.36584, "detection_": 8.0, "radiative_": 2.1, "sat": "npp", "acqdate": "2023-10-05", "acqtime": "13:M3:58", "sensor": "VF375", "state": "PB", "district": "FIROZPUR"}, {"lat": 31.6593, "lon": 75.13605, "detection_": 8.0, "radiative_": 3.9, "sat": "npp", "acqdate": "2023-10-05", "acqtime": "13:M3:58", "sensor": "VF375", "state": "PB", "district": "AMRITSAR"}, {"lat": 31.71721, "lon": 74.9541, "detection_": 8.0, "radiative_": 1.7, "sat": "npp", "acqdate": "2023-10-05", "acqtime": "13:M3:58", "sensor": "VF375", "state": "PB", "district": "AMRITSAR"}, {"lat": 31.52273, "lon": 74.6158, "detection_": 8.0, "radiative_": 3.0, "sat": "npp", "acqdate": "2023-10-05", "acqtime": "13:M3:58", "sensor": "VF375", "state": "PB", "district": "AMRITSAR"}, {"lat": 31.45398, "lon": 74.68458, "detection_": 8.0, "radiative_": 3.0, "sat": "npp", "acqdate": "2023-10-05", "acqtime": "13:M3:58", "sensor": "VF375", "state": "PB", "district": "TARN TARAN"}, {"lat": 31.83191, "lon": 74.82275, "detection_": 8.0, "radiative_": 3.1, "sat": "npp", "acqdate": "2023-10-05", "acqtime": "13:M3:58", "sensor": "VF375", "state": "PB", "district": "AMRITSAR"}, {"lat": 31.70162, "lon": 74.9445, "detection_": 8.0, "radiative_": 19.4, "sat": "npp", "acqdate": "2023-10-05", "acqtime": "13:M3:58", "sensor": "VF375", "state": "PB", "district": "AMRITSAR"}, {"lat": 31.69417, "lon": 74.9418, "detection_": 8.0, "radiative_": 5.1, "sat": "npp", "acqdate": "2023-10-05", "acqtime": "13:M3:58", "sensor": "VF375", "state": "PB", "district": "AMRITSAR"}, {"lat": 31.70499, "lon": 74.94373, "detection_": 8.0, "radiative_": 20.6, "sat": "npp", "acqdate": "2023-10-05", "acqtime": "13:M3:58", "sensor": "VF375", "state": "PB", "district": "AMRITSAR"}, {"lat": 31.68301, "lon": 74.97946, "detection_": 8.0, "radiative_": 2.5, "sat": "npp", "acqdate": "2023-10-05", "acqtime": "13:M3:58", "sensor": "VF375", "state": "PB", "district": "AMRITSAR"}, {"lat": 31.46406, "lon": 74.86879, "detection_": 8.0, "radiative_": 4.0, "sat": "npp", "acqdate": "2023-10-05", "acqtime": "13:M3:58", "sensor": "VF375", "state": "PB", "district": "TARN TARAN"}, {"lat": 31.46384, "lon": 74.84673, "detection_": 8.0, "radiative_": 2.4, "sat": "npp", "acqdate": "2023-10-05", "acqtime": "13:M3:58", "sensor": "VF375", "state": "PB", "district": "TARN TARAN"}, {"lat": 31.50338, "lon": 74.87303, "detection_": 8.0, "radiative_": 2.4, "sat": "npp", "acqdate": "2023-10-05", "acqtime": "13:M3:58", "sensor": "VF375", "state": "PB", "district": "TARN TARAN"}, {"lat": 31.91357, "lon": 74.74287, "detection_": 8.0, "radiative_": 3.6, "sat": "npp", "acqdate": "2023-10-05", "acqtime": "13:M3:58", "sensor": "VF375", "state": "PB", "district": "AMRITSAR"}, {"lat": 31.9319, "lon": 74.74749, "detection_": 8.0, "radiative_": 3.2, "sat": "npp", "acqdate": "2023-10-05", "acqtime": "13:M3:58", "sensor": "VF375", "state": "PB", "district": "AMRITSAR"}, {"lat": 31.58009, "lon": 74.89146, "detection_": 8.0, "radiative_": 3.0, "sat": "npp", "acqdate": "2023-10-05", "acqtime": "13:M3:58", "sensor": "VF375", "state": "PB", "district": "AMRITSAR"}, {"lat": 31.60099, "lon": 74.80714, "detection_": 8.0, "radiative_": 3.4, "sat": "npp", "acqdate": "2023-10-05", "acqtime": "13:M3:58", "sensor": "VF375", "state": "PB", "district": "AMRITSAR"}, {"lat": 31.60437, "lon": 74.80637, "detection_": 8.0, "radiative_": 3.4, "sat": "npp", "acqdate": "2023-10-05", "acqtime": "13:M3:58", "sensor": "VF375", "state": "PB", "district": "AMRITSAR"}, {"lat": 31.57712, "lon": 75.10617, "detection_": 8.0, "radiative_": 11.5, "sat": "npp", "acqdate": "2023-10-05", "acqtime": "13:M3:58", "sensor": "VF375", "state": "PB", "district": "AMRITSAR"}, {"lat": 31.50662, "lon": 75.24799, "detection_": 8.0, "radiative_": 1.8, "sat": "npp", "acqdate": "2023-10-05", "acqtime": "13:M3:58", "sensor": "VF375", "state": "PB", "district": "AMRITSAR"}, {"lat": 31.57956, "lon": 75.07572, "detection_": 8.0, "radiative_": 5.3, "sat": "npp", "acqdate": "2023-10-05", "acqtime": "13:M3:58", "sensor": "VF375", "state": "PB", "district": "AMRITSAR"}, {"lat": 31.76258, "lon": 75.10115, "detection_": 8.0, "radiative_": 4.2, "sat": "npp", "acqdate": "2023-10-05", "acqtime": "13:M3:58", "sensor": "VF375", "state": "PB", "district": "GURDASPUR"}, {"lat": 31.5781, "lon": 75.17554, "detection_": 8.0, "radiative_": 5.4, "sat": "npp", "acqdate": "2023-10-05", "acqtime": "13:M3:58", "sensor": "VF375", "state": "PB", "district": "AMRITSAR"}, {"lat": 31.54977, "lon": 74.8366, "detection_": 8.0, "radiative_": 4.3, "sat": "npp", "acqdate": "2023-10-05", "acqtime": "13:M3:58", "sensor": "VF375", "state": "PB", "district": "AMRITSAR"}, {"lat": 31.52347, "lon": 74.62011, "detection_": 8.0, "radiative_": 3.4, "sat": "npp", "acqdate": "2023-10-05", "acqtime": "13:M3:58", "sensor": "VF375", "state": "PB", "district": "AMRITSAR"}, {"lat": 31.66674, "lon": 74.63349, "detection_": 8.0, "radiative_": 4.0, "sat": "npp", "acqdate": "2023-10-05", "acqtime": "13:M3:58", "sensor": "VF375", "state": "PB", "district": "AMRITSAR"}, {"lat": 29.98666, "lon": 76.1217, "detection_": 8.0, "radiative_": 4.1, "sat": "npp", "acqdate": "2023-10-05", "acqtime": "13:M3:58", "sensor": "VF375", "state": "PB", "district": "PATIALA"}, {"lat": 30.05311, "lon": 76.03255, "detection_": 8.0, "radiative_": 2.3, "sat": "npp", "acqdate": "2023-10-05", "acqtime": "13:M3:58", "sensor": "VF375", "state": "PB", "district": "SANGRUR"}, {"lat": 31.61801, "lon": 74.65818, "detection_": 8.0, "radiative_": 5.1, "sat": "npp", "acqdate": "2023-10-05", "acqtime": "13:M3:58", "sensor": "VF375", "state": "PB", "district": "AMRITSAR"}, {"lat": 31.55146, "lon": 75.22492, "detection_": 8.0, "radiative_": 6.1, "sat": "npp", "acqdate": "2023-10-05", "acqtime": "13:M3:58", "sensor": "VF375", "state": "PB", "district": "AMRITSAR"}, {"lat": 31.55078, "lon": 75.22074, "detection_": 8.0, "radiative_": 6.1, "sat": "npp", "acqdate": "2023-10-05", "acqtime": "13:M3:58", "sensor": "VF375", "state": "PB", "district": "AMRITSAR"}, {"lat": 31.53924, "lon": 75.19301, "detection_": 8.0, "radiative_": 2.2, "sat": "npp", "acqdate": "2023-10-05", "acqtime": "13:M3:58", "sensor": "VF375", "state": "PB", "district": "AMRITSAR"}, {"lat": 31.5441, "lon": 75.09624, "detection_": 8.0, "radiative_": 8.8, "sat": "npp", "acqdate": "2023-10-05", "acqtime": "13:M3:58", "sensor": "VF375", "state": "PB", "district": "AMRITSAR"}, {"lat": 31.54074, "lon": 75.097, "detection_": 8.0, "radiative_": 8.8, "sat": "npp", "acqdate": "2023-10-05", "acqtime": "13:M3:58", "sensor": "VF375", "state": "PB", "district": "AMRITSAR"}, {"lat": 30.55096, "lon": 76.6937, "detection_": 8.0, "radiative_": 2.3, "sat": "npp", "acqdate": "2023-10-05", "acqtime": "13:M3:58", "sensor": "VF375", "state": "PB", "district": "PATIALA"}, {"lat": 31.73782, "lon": 75.11982, "detection_": 8.0, "radiative_": 5.1, "sat": "npp", "acqdate": "2023-10-05", "acqtime": "13:M3:58", "sensor": "VF375", "state": "PB", "district": "AMRITSAR"}, {"lat": 31.70657, "lon": 74.97408, "detection_": 8.0, "radiative_": 2.6, "sat": "npp", "acqdate": "2023-10-05", "acqtime": "13:M3:58", "sensor": "VF375", "state": "PB", "district": "AMRITSAR"}, {"lat": 31.71667, "lon": 74.97178, "detection_": 8.0, "radiative_": 4.2, "sat": "npp", "acqdate": "2023-10-05", "acqtime": "13:M3:58", "sensor": "VF375", "state": "PB", "district": "AMRITSAR"}, {"lat": 31.77714, "lon": 74.97609, "detection_": 8.0, "radiative_": 9.6, "sat": "npp", "acqdate": "2023-10-05", "acqtime": "13:M3:58", "sensor": "VF375", "state": "PB", "district": "AMRITSAR"}, {"lat": 31.07475, "lon": 74.97535, "detection_": 8.0, "radiative_": 5.1, "sat": "npp", "acqdate": "2023-10-05", "acqtime": "13:M3:58", "sensor": "VF375", "state": "PB", "district": "FIROZPUR"}, {"lat": 30.54249, "lon": 76.68309, "detection_": 8.0, "radiative_": 5.7, "sat": "npp", "acqdate": "2023-10-05", "acqtime": "13:M3:58", "sensor": "VF375", "state": "PB", "district": "PATIALA"}, {"lat": 30.28731, "lon": 76.26755, "detection_": 8.0, "radiative_": 7.7, "sat": "npp", "acqdate": "2023-10-05", "acqtime": "13:M3:58", "sensor": "VF375", "state": "PB", "district": "PATIALA"}, {"lat": 30.25501, "lon": 76.04491, "detection_": 8.0, "radiative_": 3.0, "sat": "npp", "acqdate": "2023-10-05", "acqtime": "13:M3:58", "sensor": "VF375", "state": "PB", "district": "SANGRUR"}, {"lat": 30.743, "lon": 76.53445, "detection_": 8.0, "radiative_": 9.8, "sat": "npp", "acqdate": "2023-10-05", "acqtime": "13:M3:58", "sensor": "VF375", "state": "PB", "district": "SAS NAGAR (MOHALI)"}, {"lat": 30.71965, "lon": 76.38604, "detection_": 8.0, "radiative_": 2.9, "sat": "npp", "acqdate": "2023-10-05", "acqtime": "13:M3:58", "sensor": "VF375", "state": "PB", "district": "FATEHGARH SAHIB"}, {"lat": 29.98082, "lon": 76.08533, "detection_": 8.0, "radiative_": 2.2, "sat": "npp", "acqdate": "2023-10-05", "acqtime": "13:M3:58", "sensor": "VF375", "state": "PB", "district": "PATIALA"}, {"lat": 30.87166, "lon": 76.48715, "detection_": 8.0, "radiative_": 2.2, "sat": "npp", "acqdate": "2023-10-05", "acqtime": "13:M3:58", "sensor": "VF375", "state": "PB", "district": "RUPNAGAR"}, {"lat": 29.85529, "lon": 75.40287, "detection_": 8.0, "radiative_": 6.0, "sat": "npp", "acqdate": "2023-10-05", "acqtime": "13:M3:58", "sensor": "VF375", "state": "PB", "district": "MANSA"}, {"lat": 29.85459, "lon": 75.39869, "detection_": 8.0, "radiative_": 4.1, "sat": "npp", "acqdate": "2023-10-05", "acqtime": "13:M3:58", "sensor": "VF375", "state": "PB", "district": "MANSA"}], "districts": {"AMRITSAR": 53, "BARNALA": 1, "BATHINDA": 0, "FARIDKOT": 1, "FATEHGARH SAHIB": 1, "FAZILKA": 0, "FIROZPUR": 3, "GURDASPUR": 1, "HOSHIARPUR": 0, "JALANDHAR": 3, "KAPURTHALA": 7, "LUDHIANA": 0, "MANSA": 4, "MOGA": 0, "MUKTSAR": 0, "SBS NAGAR": 0, "PATHANKOT": 0, "PATIALA": 11, "RUPNAGAR": 1, "SANGRUR": 5, "SAS NAGAR (MOHALI)": 4, "TARN TARAN": 13}}}